{
  "id": "douyin-9fb8498c65",
  "slug": "douyin-原来成语缝在汉服里",
  "platform": "douyin",
  "platformLabel": "抖音",
  "rank": 18,
  "title": "原来成语缝在汉服里",
  "summary": "抖音热榜第 18 位：原来成语缝在汉服里，当前热度为 775万热度。",
  "url": "https://www.douyin.com/search/%E5%8E%9F%E6%9D%A5%E6%88%90%E8%AF%AD%E7%BC%9D%E5%9C%A8%E6%B1%89%E6%9C%8D%E9%87%8C?type=general",
  "hotValue": "775万热度",
  "author": "",
  "publishedAt": "2026-06-14T01:21:50.419Z",
  "fetchedAt": "2026-06-14T01:43:01.057Z",
  "tags": [
    "抖音",
    "社媒热榜",
    "每日趋势"
  ],
  "source": "UAPI Hotboard",
  "sourceStatus": "live"
}