{
  "id": "douyin-4d019ebe62",
  "slug": "douyin-阿根廷2-1逆转绝杀英格兰",
  "platform": "douyin",
  "platformLabel": "抖音",
  "rank": 1,
  "title": "阿根廷2:1逆转绝杀英格兰",
  "summary": "抖音热榜第 1 位：阿根廷2:1逆转绝杀英格兰，当前热度为 1,225万热度。",
  "url": "https://www.douyin.com/search/%E9%98%BF%E6%A0%B9%E5%BB%B72%3A1%E9%80%86%E8%BD%AC%E7%BB%9D%E6%9D%80%E8%8B%B1%E6%A0%BC%E5%85%B0?type=general",
  "hotValue": "1,225万热度",
  "author": "",
  "publishedAt": "2026-07-16T00:31:59.439Z",
  "fetchedAt": "2026-07-16T00:55:17.746Z",
  "tags": [
    "抖音",
    "社媒热榜",
    "每日趋势"
  ],
  "source": "UAPI Hotboard",
  "sourceStatus": "live"
}