{
  "id": "douyin-a98ad5c504",
  "slug": "douyin-hyrox穿搭赢一半",
  "platform": "douyin",
  "platformLabel": "抖音",
  "rank": 30,
  "title": "HYROX穿搭赢一半",
  "summary": "抖音热榜第 30 位：HYROX穿搭赢一半，当前热度为 770万热度。",
  "url": "https://www.douyin.com/search/HYROX%E7%A9%BF%E6%90%AD%E8%B5%A2%E4%B8%80%E5%8D%8A?type=general",
  "hotValue": "770万热度",
  "author": "",
  "publishedAt": "2026-07-05T01:01:48.110Z",
  "fetchedAt": "2026-07-05T01:14:49.444Z",
  "tags": [
    "抖音",
    "社媒热榜",
    "每日趋势"
  ],
  "source": "UAPI Hotboard",
  "sourceStatus": "live"
}