{
  "id": "douyin-8ee2e4f2a9",
  "slug": "douyin-vibecoding作品夯爆了",
  "platform": "douyin",
  "platformLabel": "抖音",
  "rank": 29,
  "title": "VibeCoding作品夯爆了",
  "summary": "抖音热榜第 29 位：VibeCoding作品夯爆了，当前热度为 771万热度。",
  "url": "https://www.douyin.com/search/VibeCoding%E4%BD%9C%E5%93%81%E5%A4%AF%E7%88%86%E4%BA%86?type=general",
  "hotValue": "771万热度",
  "author": "",
  "publishedAt": "2026-06-28T01:16:49.777Z",
  "fetchedAt": "2026-06-28T01:33:05.335Z",
  "tags": [
    "抖音",
    "社媒热榜",
    "每日趋势"
  ],
  "source": "UAPI Hotboard",
  "sourceStatus": "live"
}