{
  "id": "douyin-ed0b1bb1bf",
  "slug": "douyin-幸福是一碗巨无霸肘子盖饭",
  "platform": "douyin",
  "platformLabel": "抖音",
  "rank": 32,
  "title": "幸福是一碗巨无霸肘子盖饭",
  "summary": "抖音热榜第 32 位：幸福是一碗巨无霸肘子盖饭，当前热度为 772万热度。",
  "url": "https://www.douyin.com/search/%E5%B9%B8%E7%A6%8F%E6%98%AF%E4%B8%80%E7%A2%97%E5%B7%A8%E6%97%A0%E9%9C%B8%E8%82%98%E5%AD%90%E7%9B%96%E9%A5%AD?type=general",
  "hotValue": "772万热度",
  "author": "",
  "publishedAt": "2026-06-05T01:21:54.091Z",
  "fetchedAt": "2026-06-05T01:36:23.611Z",
  "tags": [
    "抖音",
    "社媒热榜",
    "每日趋势"
  ],
  "source": "UAPI Hotboard",
  "sourceStatus": "live"
}