{
  "id": "douyin-c9557f6268",
  "slug": "douyin-龙舟踏浪送福来",
  "platform": "douyin",
  "platformLabel": "抖音",
  "rank": 35,
  "title": "龙舟踏浪送福来",
  "summary": "抖音热榜第 35 位：龙舟踏浪送福来，当前热度为 773万热度。",
  "url": "https://www.douyin.com/search/%E9%BE%99%E8%88%9F%E8%B8%8F%E6%B5%AA%E9%80%81%E7%A6%8F%E6%9D%A5?type=general",
  "hotValue": "773万热度",
  "author": "",
  "publishedAt": "2026-06-20T01:06:47.208Z",
  "fetchedAt": "2026-06-20T01:36:36.655Z",
  "tags": [
    "抖音",
    "社媒热榜",
    "每日趋势"
  ],
  "source": "UAPI Hotboard",
  "sourceStatus": "live"
}