{
  "id": "douyin-cec411303c",
  "slug": "douyin-天涯社区恢复访问",
  "platform": "douyin",
  "platformLabel": "抖音",
  "rank": 1,
  "title": "天涯社区恢复访问",
  "summary": "抖音热榜第 1 位：天涯社区恢复访问，当前热度为 1,208万热度。",
  "url": "https://www.douyin.com/search/%E5%A4%A9%E6%B6%AF%E7%A4%BE%E5%8C%BA%E6%81%A2%E5%A4%8D%E8%AE%BF%E9%97%AE?type=general",
  "hotValue": "1,208万热度",
  "author": "",
  "publishedAt": "2026-06-01T19:32:00.859Z",
  "fetchedAt": "2026-06-01T23:31:03.035Z",
  "tags": [
    "抖音",
    "社媒热榜",
    "每日趋势"
  ],
  "source": "UAPI Hotboard",
  "sourceStatus": "live"
}