{
  "id": "douyin-17581c7cce",
  "slug": "douyin-哈兰德给女朋友过生日",
  "platform": "douyin",
  "platformLabel": "抖音",
  "rank": 16,
  "title": "哈兰德给女朋友过生日",
  "summary": "抖音热榜第 16 位：哈兰德给女朋友过生日，当前热度为 766万热度。",
  "url": "https://www.douyin.com/search/%E5%93%88%E5%85%B0%E5%BE%B7%E7%BB%99%E5%A5%B3%E6%9C%8B%E5%8F%8B%E8%BF%87%E7%94%9F%E6%97%A5?type=general",
  "hotValue": "766万热度",
  "author": "",
  "publishedAt": "2026-07-16T00:31:59.439Z",
  "fetchedAt": "2026-07-16T00:55:17.746Z",
  "tags": [
    "抖音",
    "社媒热榜",
    "每日趋势"
  ],
  "source": "UAPI Hotboard",
  "sourceStatus": "live"
}