{
  "id": "douyin-32e303eeee",
  "slug": "douyin-陈赫-哈兰德太猛了",
  "platform": "douyin",
  "platformLabel": "抖音",
  "rank": 25,
  "title": "陈赫：哈兰德太猛了",
  "summary": "抖音热榜第 25 位：陈赫：哈兰德太猛了，当前热度为 767万热度。",
  "url": "https://www.douyin.com/search/%E9%99%88%E8%B5%AB%EF%BC%9A%E5%93%88%E5%85%B0%E5%BE%B7%E5%A4%AA%E7%8C%9B%E4%BA%86?type=general",
  "hotValue": "767万热度",
  "author": "",
  "publishedAt": "2026-07-06T00:41:52.501Z",
  "fetchedAt": "2026-07-06T01:15:20.259Z",
  "tags": [
    "抖音",
    "社媒热榜",
    "每日趋势"
  ],
  "source": "UAPI Hotboard",
  "sourceStatus": "live"
}