{
  "id": "douyin-1115d80275",
  "slug": "douyin-哈兰德把抖音当朋友圈发",
  "platform": "douyin",
  "platformLabel": "抖音",
  "rank": 26,
  "title": "哈兰德把抖音当朋友圈发",
  "summary": "抖音热榜第 26 位：哈兰德把抖音当朋友圈发，当前热度为 773万热度。",
  "url": "https://www.douyin.com/search/%E5%93%88%E5%85%B0%E5%BE%B7%E6%8A%8A%E6%8A%96%E9%9F%B3%E5%BD%93%E6%9C%8B%E5%8F%8B%E5%9C%88%E5%8F%91?type=general",
  "hotValue": "773万热度",
  "author": "",
  "publishedAt": "2026-07-01T00:51:48.303Z",
  "fetchedAt": "2026-07-01T01:38:34.063Z",
  "tags": [
    "抖音",
    "社媒热榜",
    "每日趋势"
  ],
  "source": "UAPI Hotboard",
  "sourceStatus": "live"
}