{
  "id": "douyin-0a75f47dca",
  "slug": "douyin-天空灰得像哭过",
  "platform": "douyin",
  "platformLabel": "抖音",
  "rank": 39,
  "title": "天空灰得像哭过",
  "summary": "抖音热榜第 39 位：天空灰得像哭过，当前热度为 766万热度。",
  "url": "https://www.douyin.com/search/%E5%A4%A9%E7%A9%BA%E7%81%B0%E5%BE%97%E5%83%8F%E5%93%AD%E8%BF%87?type=general",
  "hotValue": "766万热度",
  "author": "",
  "publishedAt": "2026-06-27T01:01:44.618Z",
  "fetchedAt": "2026-06-27T01:28:59.935Z",
  "tags": [
    "抖音",
    "社媒热榜",
    "每日趋势"
  ],
  "source": "UAPI Hotboard",
  "sourceStatus": "live"
}