{
  "id": "douyin-0089f37ee8",
  "slug": "douyin-中国u17男足不敌坦桑尼亚",
  "platform": "douyin",
  "platformLabel": "抖音",
  "rank": 2,
  "title": "中国U17男足不敌坦桑尼亚",
  "summary": "抖音热榜第 2 位：中国U17男足不敌坦桑尼亚，当前热度为 1,126万热度。",
  "url": "https://www.douyin.com/search/%E4%B8%AD%E5%9B%BDU17%E7%94%B7%E8%B6%B3%E4%B8%8D%E6%95%8C%E5%9D%A6%E6%A1%91%E5%B0%BC%E4%BA%9A?type=general",
  "hotValue": "1,126万热度",
  "author": "",
  "publishedAt": "2026-07-09T00:12:30.690Z",
  "fetchedAt": "2026-07-09T01:08:55.561Z",
  "tags": [
    "抖音",
    "社媒热榜",
    "每日趋势"
  ],
  "source": "UAPI Hotboard",
  "sourceStatus": "live"
}