{
  "id": "douyin-a467d0be0c",
  "slug": "douyin-天空灰得像哭过",
  "platform": "douyin",
  "platformLabel": "抖音",
  "rank": 36,
  "title": "天空灰得像哭过",
  "summary": "抖音热榜第 36 位：天空灰得像哭过，当前热度为 771万热度。",
  "url": "https://www.douyin.com/search/%E5%A4%A9%E7%A9%BA%E7%81%B0%E5%BE%97%E5%83%8F%E5%93%AD%E8%BF%87?type=general",
  "hotValue": "771万热度",
  "author": "",
  "publishedAt": "2026-06-26T01:16:47.107Z",
  "fetchedAt": "2026-06-26T01:35:46.940Z",
  "tags": [
    "抖音",
    "社媒热榜",
    "每日趋势"
  ],
  "source": "UAPI Hotboard",
  "sourceStatus": "live"
}