{
  "id": "douyin-1c4836c354",
  "slug": "douyin-当我意识到唱歌时表情不是必须",
  "platform": "douyin",
  "platformLabel": "抖音",
  "rank": 6,
  "title": "当我意识到唱歌时表情不是必须",
  "summary": "抖音热榜第 6 位：当我意识到唱歌时表情不是必须，当前热度为 1,088万热度。",
  "url": "https://www.douyin.com/search/%E5%BD%93%E6%88%91%E6%84%8F%E8%AF%86%E5%88%B0%E5%94%B1%E6%AD%8C%E6%97%B6%E8%A1%A8%E6%83%85%E4%B8%8D%E6%98%AF%E5%BF%85%E9%A1%BB?type=general",
  "hotValue": "1,088万热度",
  "author": "",
  "publishedAt": "2026-06-02T00:47:03.609Z",
  "fetchedAt": "2026-06-02T01:44:46.936Z",
  "tags": [
    "抖音",
    "社媒热榜",
    "每日趋势"
  ],
  "source": "UAPI Hotboard",
  "sourceStatus": "live"
}