{
  "id": "douyin-c80192a75f",
  "slug": "douyin-丁禹兮消散对白年度十大金曲",
  "platform": "douyin",
  "platformLabel": "抖音",
  "rank": 23,
  "title": "丁禹兮消散对白年度十大金曲",
  "summary": "抖音热榜第 23 位：丁禹兮消散对白年度十大金曲，当前热度为 774万热度。",
  "url": "https://www.douyin.com/search/%E4%B8%81%E7%A6%B9%E5%85%AE%E6%B6%88%E6%95%A3%E5%AF%B9%E7%99%BD%E5%B9%B4%E5%BA%A6%E5%8D%81%E5%A4%A7%E9%87%91%E6%9B%B2?type=general",
  "hotValue": "774万热度",
  "author": "",
  "publishedAt": "2026-06-24T19:47:19.273Z",
  "fetchedAt": "2026-06-25T01:32:05.679Z",
  "tags": [
    "抖音",
    "社媒热榜",
    "每日趋势"
  ],
  "source": "UAPI Hotboard",
  "sourceStatus": "live"
}