{
  "id": "weibo-a94ba3951d",
  "slug": "weibo-丈夫抢走孩子爷爷放话拘留也不还",
  "platform": "weibo",
  "platformLabel": "微博",
  "rank": 14,
  "title": "丈夫抢走孩子爷爷放话拘留也不还",
  "summary": "微博热榜第 14 位：丈夫抢走孩子爷爷放话拘留也不还，当前热度为 40万热度。",
  "url": "https://s.weibo.com/weibo?q=%23%E4%B8%88%E5%A4%AB%E6%8A%A2%E8%B5%B0%E5%AD%A9%E5%AD%90%E7%88%B7%E7%88%B7%E6%94%BE%E8%AF%9D%E6%8B%98%E7%95%99%E4%B9%9F%E4%B8%8D%E8%BF%98%23",
  "hotValue": "40万热度",
  "author": "",
  "publishedAt": "2026-05-29 09:31:02",
  "fetchedAt": "2026-05-29T01:31:40.482Z",
  "tags": [
    "微博",
    "社媒热榜",
    "每日趋势"
  ],
  "source": "UAPI Hotboard",
  "sourceStatus": "live"
}