{
  "id": "weibo-273fbd6a85",
  "slug": "weibo-女子买验孕笔用后仅退款还嘲讽商家",
  "platform": "weibo",
  "platformLabel": "微博",
  "rank": 47,
  "title": "女子买验孕笔用后仅退款还嘲讽商家",
  "summary": "微博热榜第 47 位：女子买验孕笔用后仅退款还嘲讽商家，当前热度为 13万热度。",
  "url": "https://s.weibo.com/weibo?q=%23%E5%A5%B3%E5%AD%90%E4%B9%B0%E9%AA%8C%E5%AD%95%E7%AC%94%E7%94%A8%E5%90%8E%E4%BB%85%E9%80%80%E6%AC%BE%E8%BF%98%E5%98%B2%E8%AE%BD%E5%95%86%E5%AE%B6%23",
  "hotValue": "13万热度",
  "author": "",
  "publishedAt": "2026-06-04 10:00:02",
  "fetchedAt": "2026-06-04T02:04:50.003Z",
  "tags": [
    "微博",
    "社媒热榜",
    "每日趋势"
  ],
  "source": "UAPI Hotboard",
  "sourceStatus": "live"
}