{
  "id": "weibo-b7b93e9203",
  "slug": "weibo-武汉21岁大学生卖1500元手搓蝴蝶爆火",
  "platform": "weibo",
  "platformLabel": "微博",
  "rank": 28,
  "title": "武汉21岁大学生卖1500元手搓蝴蝶爆火",
  "summary": "微博热榜第 28 位：武汉21岁大学生卖1500元手搓蝴蝶爆火，当前热度为 30万热度。",
  "url": "https://s.weibo.com/weibo?q=%23%E6%AD%A6%E6%B1%8921%E5%B2%81%E5%A4%A7%E5%AD%A6%E7%94%9F%E5%8D%961500%E5%85%83%E6%89%8B%E6%90%93%E8%9D%B4%E8%9D%B6%E7%88%86%E7%81%AB%23",
  "hotValue": "30万热度",
  "author": "",
  "publishedAt": "2026-05-25 08:10:02",
  "fetchedAt": "2026-05-25T00:18:31.897Z",
  "tags": [
    "微博",
    "社媒热榜",
    "每日趋势"
  ],
  "source": "UAPI Hotboard",
  "sourceStatus": "live"
}