{
  "id": "weibo-029d91646b",
  "slug": "weibo-黄仁勋躺地喝啤酒",
  "platform": "weibo",
  "platformLabel": "微博",
  "rank": 28,
  "title": "黄仁勋躺地喝啤酒",
  "summary": "微博热榜第 28 位：黄仁勋躺地喝啤酒，当前热度为 24万热度。",
  "url": "https://s.weibo.com/weibo?q=%23%E9%BB%84%E4%BB%81%E5%8B%8B%E8%BA%BA%E5%9C%B0%E5%96%9D%E5%95%A4%E9%85%92%23",
  "hotValue": "24万热度",
  "author": "",
  "publishedAt": "2026-06-04 10:00:02",
  "fetchedAt": "2026-06-04T02:04:50.003Z",
  "tags": [
    "微博",
    "社媒热榜",
    "每日趋势"
  ],
  "source": "UAPI Hotboard",
  "sourceStatus": "live"
}