{
  "id": "weibo-a81e747398",
  "slug": "weibo-现在就出发4-金晨",
  "platform": "weibo",
  "platformLabel": "微博",
  "rank": 23,
  "title": "现在就出发4 金晨",
  "summary": "微博热榜第 23 位：现在就出发4 金晨，当前热度为 41万热度。",
  "url": "https://s.weibo.com/weibo?q=%23%E7%8E%B0%E5%9C%A8%E5%B0%B1%E5%87%BA%E5%8F%914+%E9%87%91%E6%99%A8%23",
  "hotValue": "41万热度",
  "author": "",
  "publishedAt": "2026-07-01 09:29:19",
  "fetchedAt": "2026-07-01T01:38:34.062Z",
  "tags": [
    "微博",
    "社媒热榜",
    "每日趋势"
  ],
  "source": "UAPI Hotboard",
  "sourceStatus": "live"
}