{
  "id": "weibo-3348dfc910",
  "slug": "weibo-加拿大开幕式-翻车",
  "platform": "weibo",
  "platformLabel": "微博",
  "rank": 1,
  "title": "加拿大开幕式 翻车",
  "summary": "微博热榜第 1 位：加拿大开幕式 翻车，当前热度为 1,277万热度。",
  "url": "https://s.weibo.com/weibo?q=%23%E5%8A%A0%E6%8B%BF%E5%A4%A7%E5%BC%80%E5%B9%95%E5%BC%8F+%E7%BF%BB%E8%BD%A6%23",
  "hotValue": "1,277万热度",
  "author": "",
  "publishedAt": "2026-06-13 09:35:43",
  "fetchedAt": "2026-06-13T01:37:59.320Z",
  "tags": [
    "微博",
    "社媒热榜",
    "每日趋势"
  ],
  "source": "UAPI Hotboard",
  "sourceStatus": "live"
}