{
  "id": "weibo-01e7d82c31",
  "slug": "weibo-多重硬核成就彰显高质量发展底气",
  "platform": "weibo",
  "platformLabel": "微博",
  "rank": 3,
  "title": "多重硬核成就彰显高质量发展底气",
  "summary": "微博热榜第 3 位：多重硬核成就彰显高质量发展底气，当前热度为 747万热度。",
  "url": "https://s.weibo.com/weibo?q=%23%E5%A4%9A%E9%87%8D%E7%A1%AC%E6%A0%B8%E6%88%90%E5%B0%B1%E5%BD%B0%E6%98%BE%E9%AB%98%E8%B4%A8%E9%87%8F%E5%8F%91%E5%B1%95%E5%BA%95%E6%B0%94%23",
  "hotValue": "747万热度",
  "author": "",
  "publishedAt": "2026-07-04T01:05:54.745Z",
  "fetchedAt": "2026-07-04T01:06:37.651Z",
  "tags": [
    "微博",
    "社媒热榜",
    "每日趋势"
  ],
  "source": "UAPI Hotboard",
  "sourceStatus": "live"
}