{
  "id": "weibo-6c51b7e7f5",
  "slug": "weibo-王鹤棣咸鱼飞升",
  "platform": "weibo",
  "platformLabel": "微博",
  "rank": 14,
  "title": "王鹤棣咸鱼飞升",
  "summary": "微博热榜第 14 位：王鹤棣咸鱼飞升，当前热度为 41万热度。",
  "url": "https://s.weibo.com/weibo?q=%23%E7%8E%8B%E9%B9%A4%E6%A3%A3%E5%92%B8%E9%B1%BC%E9%A3%9E%E5%8D%87%23",
  "hotValue": "41万热度",
  "author": "",
  "publishedAt": "2026-05-28 09:14:01",
  "fetchedAt": "2026-05-28T01:23:06.644Z",
  "tags": [
    "微博",
    "社媒热榜",
    "每日趋势"
  ],
  "source": "UAPI Hotboard",
  "sourceStatus": "live"
}