{
  "id": "weibo-b3c0727ed2",
  "slug": "weibo-美军连续第八晚袭击伊朗",
  "platform": "weibo",
  "platformLabel": "微博",
  "rank": 23,
  "title": "美军连续第八晚袭击伊朗",
  "summary": "微博热榜第 23 位：美军连续第八晚袭击伊朗，当前热度为 23万热度。",
  "url": "https://s.weibo.com/weibo?q=%23%E7%BE%8E%E5%86%9B%E8%BF%9E%E7%BB%AD%E7%AC%AC%E5%85%AB%E6%99%9A%E8%A2%AD%E5%87%BB%E4%BC%8A%E6%9C%97%23",
  "hotValue": "23万热度",
  "author": "",
  "publishedAt": "2026-07-19T00:15:20.350Z",
  "fetchedAt": "2026-07-19T00:15:20.464Z",
  "tags": [
    "微博",
    "社媒热榜",
    "每日趋势"
  ],
  "source": "UAPI Hotboard",
  "sourceStatus": "live"
}