{
  "id": "weibo-b81f3abce4",
  "slug": "weibo-余承东坦言自己留的算力很有限",
  "platform": "weibo",
  "platformLabel": "微博",
  "rank": 18,
  "title": "余承东坦言自己留的算力很有限",
  "summary": "微博热榜第 18 位：余承东坦言自己留的算力很有限，当前热度为 33万热度。",
  "url": "https://s.weibo.com/weibo?q=%23%E4%BD%99%E6%89%BF%E4%B8%9C%E5%9D%A6%E8%A8%80%E8%87%AA%E5%B7%B1%E7%95%99%E7%9A%84%E7%AE%97%E5%8A%9B%E5%BE%88%E6%9C%89%E9%99%90%23",
  "hotValue": "33万热度",
  "author": "",
  "publishedAt": "2026-06-13 09:35:43",
  "fetchedAt": "2026-06-13T01:37:59.320Z",
  "tags": [
    "微博",
    "社媒热榜",
    "每日趋势"
  ],
  "source": "UAPI Hotboard",
  "sourceStatus": "live"
}