{
  "id": "weibo-87c80231d5",
  "slug": "weibo-办婚礼未领证分手后男方诉返22万",
  "platform": "weibo",
  "platformLabel": "微博",
  "rank": 4,
  "title": "办婚礼未领证分手后男方诉返22万",
  "summary": "微博热榜第 4 位：办婚礼未领证分手后男方诉返22万，当前热度为 66万热度。",
  "url": "https://s.weibo.com/weibo?q=%23%E5%8A%9E%E5%A9%9A%E7%A4%BC%E6%9C%AA%E9%A2%86%E8%AF%81%E5%88%86%E6%89%8B%E5%90%8E%E7%94%B7%E6%96%B9%E8%AF%89%E8%BF%9422%E4%B8%87%23",
  "hotValue": "66万热度",
  "author": "",
  "publishedAt": "2026-06-05 09:36:13",
  "fetchedAt": "2026-06-05T01:36:23.614Z",
  "tags": [
    "微博",
    "社媒热榜",
    "每日趋势"
  ],
  "source": "UAPI Hotboard",
  "sourceStatus": "live"
}