{
  "slug": "2026-06-19",
  "date": "2026-06-19",
  "title": "2026-06-19 社媒雷达日报",
  "description": "小红书、抖音、微博每日热榜聚合。",
  "generatedAt": "2026-06-19T02:14:58.693Z",
  "stats": {
    "totalItems": 120,
    "xiaohongshuItems": 20,
    "douyinItems": 50,
    "weiboItems": 50
  },
  "sections": {
    "xiaohongshu": [
      "xiaohongshu-7a488fc999",
      "xiaohongshu-bbdba4cc5c",
      "xiaohongshu-196a95f29c",
      "xiaohongshu-50afbd263f",
      "xiaohongshu-7f3c483657",
      "xiaohongshu-803950de60",
      "xiaohongshu-19097226f2",
      "xiaohongshu-fd3120cad5",
      "xiaohongshu-98dda1a109",
      "xiaohongshu-1e3a607650",
      "xiaohongshu-d0342c9595",
      "xiaohongshu-1d5fadf199",
      "xiaohongshu-46c3bee551",
      "xiaohongshu-918dd37fdd",
      "xiaohongshu-8fac2e8924",
      "xiaohongshu-9a81e04952",
      "xiaohongshu-3c40d143b8",
      "xiaohongshu-333e1b5af9",
      "xiaohongshu-ed085a82af",
      "xiaohongshu-1fe471df8a"
    ],
    "douyin": [
      "douyin-e58956ea76",
      "douyin-f76892b362",
      "douyin-6018189433",
      "douyin-f4f3870971",
      "douyin-c54e8b315b",
      "douyin-03987f448e",
      "douyin-37fb14cd92",
      "douyin-1fe4b1f53b",
      "douyin-48ca535284",
      "douyin-ad9f763395",
      "douyin-921cf791ec",
      "douyin-c4a917f0f6",
      "douyin-f6ad784407",
      "douyin-7cd5a217f0",
      "douyin-0370c0245e",
      "douyin-e3146a9d97",
      "douyin-5e91b2c269",
      "douyin-dfaa951d75",
      "douyin-67a3de06ac",
      "douyin-5770677329",
      "douyin-74b56c5f37",
      "douyin-20001f5de6",
      "douyin-a8289334f4",
      "douyin-52f497cfd6",
      "douyin-9b511aa79f",
      "douyin-426665357f",
      "douyin-39a8c9605a",
      "douyin-7c0707bde5",
      "douyin-c163a21af9",
      "douyin-21aaa22ba7",
      "douyin-e438f63ac6",
      "douyin-5051d1e9a1",
      "douyin-484da080f6",
      "douyin-9ba076774e",
      "douyin-6c1ea7535f",
      "douyin-775d21404b",
      "douyin-21f89e866c",
      "douyin-56d8451f6f",
      "douyin-8de67a37ed",
      "douyin-2f76c183d9",
      "douyin-c849274c4a",
      "douyin-01ff2750c4",
      "douyin-2f684a7b3a",
      "douyin-546cf3855f",
      "douyin-a25daef3e9",
      "douyin-c58ec4ca26",
      "douyin-9f02c74fce",
      "douyin-b20baf9129",
      "douyin-2e1189c196",
      "douyin-77154d2921"
    ],
    "weibo": [
      "weibo-258927d912",
      "weibo-d015d02fb2",
      "weibo-823cefc09e",
      "weibo-1a76e83e5f",
      "weibo-2467ebeda8",
      "weibo-50da152ca9",
      "weibo-9e2981df1e",
      "weibo-465275abe7",
      "weibo-f1c35d8d6a",
      "weibo-935e7cbe2c",
      "weibo-e2aeaa072c",
      "weibo-3811f13e67",
      "weibo-41e7978654",
      "weibo-aab778c152",
      "weibo-7dbcdac93d",
      "weibo-569d18c1ee",
      "weibo-2addda5044",
      "weibo-0ace36c173",
      "weibo-7981fd6e53",
      "weibo-d849e7a7d0",
      "weibo-28cfe26578",
      "weibo-38e884552c",
      "weibo-9bd739d555",
      "weibo-c943ad90be",
      "weibo-bf06aa5ab0",
      "weibo-88019dd187",
      "weibo-100af38fec",
      "weibo-3797ea8809",
      "weibo-edaa44fc9a",
      "weibo-40f318811d",
      "weibo-eca3dd70ef",
      "weibo-488014bd37",
      "weibo-717b3424b7",
      "weibo-0a6b202a4a",
      "weibo-de69e53a57",
      "weibo-df0e671229",
      "weibo-3833896cd9",
      "weibo-adbed7ae8a",
      "weibo-caa97c1518",
      "weibo-10cf7143ab",
      "weibo-168b8d3cca",
      "weibo-56ae92f703",
      "weibo-9566c5e579",
      "weibo-b00da40cb6",
      "weibo-0c3f805746",
      "weibo-b3f500cce8",
      "weibo-2b08b0954d",
      "weibo-34bf71295c",
      "weibo-6b932d8577",
      "weibo-bcdd2c8c1c"
    ]
  },
  "sources": [
    "60s API Rednote",
    "UAPI Hotboard"
  ]
}