{
  "source": "GDELT",
  "category": "global",
  "originalTitle": "Đức tham vọng dẫn đầu thế giới về công nghệ thu giữ và lưu trữ CO₂",
  "summary": "GDELT 收录时间：20260516T050000Z",
  "content": "Đức tham vọng dẫn đầu thế giới về công nghệ thu giữ và lưu trữ CO₂",
  "url": "https://baomoi.com/duc-tham-vong-dan-dau-the-gioi-ve-cong-nghe-thu-giu-va-luu-tru-co2-c55170362.epi",
  "publishedAt": "",
  "domain": "baomoi.com",
  "id": "gdelt-62753ce9",
  "slug": "gdelt-62753ce9",
  "fetchedAt": "2026-06-07T01:35:45.493Z",
  "score": 56,
  "sourceWeight": 95,
  "tags": [
    "全球"
  ],
  "rank": 19,
  "contentStatus": "fetch-failed",
  "chineseTitle": "德国立志在二氧化碳捕获和储存技术方面处于世界领先地位",
  "chineseSummary": "GDELT 收录时间：20260516T050000Z",
  "chineseContent": "德国立志在二氧化碳捕获和储存技术方面处于世界领先地位",
  "whyItMatters": "这条信息属于全球新闻信号，适合用于观察外部环境、政策变化、地缘风险和市场情绪。",
  "translationStatus": "translated"
}