{
  "source": "Guardian",
  "category": "global",
  "originalTitle": "Lead prosecutor withdraws from criminal case against James Comey",
  "summary": "DoJ filing did not say why Timothy Severo is replacing Matthew Petracca in case over ex-FBI director’s ‘86 47’ post",
  "content": "The lead prosecutor in former FBI director James Comey’s case over a social media post has withdrawn from the case, according to a new court filing. The justice department filed notice with the court on Friday evening that Matthew Petracca, a prosecutor from the US attorney’s office for the eastern district of North Carolina, had been replaced by assistant US attorney Timothy Severo. The documents did not include any explanation for the change. A justice department spokesperson did not immediately respond to a request for comment from the Guardian. Comey was indicted in North Carolina in April 2026 over a photograph he posted last year of seashells arranged in the numbers “86 47” – a message the justice department says amounts to a threat against Trump, the 47th US president. The former FBI director is being indicted on two counts of threatening the president and transmitting a threat in interstate commerce. If convicted, he faces up to 10 years in prison. In response to the indictment, Comey posted a video to his personal Substack, where he defended his innocence. “Well, they’re back,” he said in the video. “This time, about a picture of seashells on a North Carolina beach a year ago. And this won’t be the end of it, but nothing has changed with me. I am still innocent. I am still not afraid. And I still believe in the independent federal judiciary. So, let’s go.” The latest charges arrived months after the failure of an effort by the justice department to prosecute Comey for allegedly lying to Congress. That indictment was tossed out by a federal judge in Virginia who ruled that the prosecutor overseeing the case had been wrongfully appointed. Former prosecutors have said that the latest charges against Comey are weaker than the earlier ones and speak to acting attorney general Todd Blanche’s ambition to quickly meet Trump’s desires. Blanche was tapped to lead the DoJ following the firing of attorney general Pam Bondi. “The descent to the bottom at DoJ has accelerated since Bondi’s departure – an apparent casualty of Blanche’s ambition,” Michael Bromwich, a former inspector general at the justice department, previously told the Guardian. Legal experts also argued that the second indictment of Comey, a top target of Donald Trump in his quest for revenge against critics, suggests more charges could be coming against other Trump opponents as the president continues to use the department of justice to attack perceived political enemies. Trump’s grievances with Comey date back to the president’s first term, when he led the bureau’s counterintelligence investigation into Trump’s ties to Russia. Trump fired Comey as FBI director in 2017, four years into his 10-year term. Comey’s trial is set to begin on 21 October in North Carolina.",
  "url": "https://www.theguardian.com/us-news/2026/may/31/prosecutor-leaves-james-comey-case-doj",
  "publishedAt": "2026-05-31T22:04:57.000Z",
  "id": "guardian-c43613b0",
  "slug": "guardian-c43613b0",
  "fetchedAt": "2026-06-01T01:38:04.882Z",
  "score": 77,
  "sourceWeight": 88,
  "tags": [
    "全球"
  ],
  "rank": 15,
  "contentStatus": "source-fulltext",
  "chineseTitle": "首席检察官退出针对詹姆斯·科米的刑事案件",
  "chineseSummary": "美国司法部提交的文件没有说明为什么蒂莫西·塞韦罗 (Timothy Severo) 会取代马修·佩特拉卡 (Matthew Petracca)，以应对前联邦调查局 (FBI) 局长“86 47”职位的案件",
  "chineseContent": "根据一份新的法庭文件，前联邦调查局局长詹姆斯·科米因社交媒体帖子一案的首席检察官已退出此案。司法部周五晚上向法院提交通知，北卡罗来纳州东区美国检察官办公室检察官马修·佩特拉卡(Matthew Petracca)已被美国助理检察官蒂莫西·塞维罗(Timothy Severo)接替。这些文件没有对这一变化做出任何解释。司法部发言人没有立即回应《卫报》的置评请求。科米于 2026 年 4 月在北卡罗来纳州被起诉，原因是他去年发布了一张贝壳排列成数字“86 47”的照片——司法部称这一信息相当于对美国第 47 任总统特朗普的威胁。这位前联邦调查局局长因威胁总统和在州际商业中传播威胁两项罪名被起诉。如果罪名成立，他将面临最高 10 年的监禁。作为对起诉书的回应，科米在他的个人 Substack 上发布了一段视频，捍卫了自己的清白。 “好吧，他们回来了，”他在视频中说道。 “这一次，是关于一年前北卡罗来纳州海滩上贝壳的照片。这不会是结束，但我什么都没有改变。我仍然是无辜的。我仍然不害怕。而且我仍然相信独立的联邦司法机构。所以，我们走吧。”最新的指控是在司法部未能起诉科米涉嫌向国会撒谎的几个月后提出的。该起诉书被弗吉尼亚州的一名联邦法官驳回，他裁定负责此案的检察官的任命是错误的。前检察官表示，对科米的最新指控比之前的指控要弱，并与代理律师进行了交谈",
  "whyItMatters": "这条信息属于全球新闻信号，适合用于观察外部环境、政策变化、地缘风险和市场情绪。",
  "translationStatus": "translated"
}