{
  "source": "Investing",
  "category": "finance",
  "originalTitle": "Taiwan Overtakes India: The AI Concentration Trade",
  "summary": "",
  "url": "https://www.investing.com/analysis/taiwan-overtakes-india-the-ai-concentration-trade-200681064",
  "publishedAt": "2026-05-28T16:38:00.000Z",
  "id": "investing-ba60f331",
  "slug": "investing-ba60f331",
  "content": "Taiwan Overtakes India: The AI Concentration Trade",
  "fetchedAt": "2026-05-29T01:30:53.525Z",
  "score": 80,
  "sourceWeight": 80,
  "tags": [
    "AI"
  ],
  "rank": 30,
  "contentStatus": "article-extracted",
  "chineseTitle": "台湾超越印度：AI 集中度贸易",
  "chineseSummary": "该条目暂未抓取到摘要，建议点击原文链接核对完整信息。",
  "chineseContent": "台湾超越印度：人工智能集中度贸易",
  "whyItMatters": "这条信息属于财经市场信号，适合用于观察利率、汇率、股债商品、金融机构和宏观政策变化。",
  "translationStatus": "translated"
}