{
  "source": "Product Hunt",
  "category": "ai-tech",
  "originalTitle": "Agent A by Ahrefs",
  "summary": "The AI Marketing Agent Powered by Ahrefs Data Discussion | Link",
  "url": "https://www.producthunt.com/products/ahrefs",
  "publishedAt": "2026-05-28T15:00:52.000Z",
  "id": "product-hunt-cf2d5109",
  "slug": "product-hunt-cf2d5109",
  "content": "The AI Marketing Agent Powered by Ahrefs Data Discussion | Link",
  "fetchedAt": "2026-05-31T01:33:45.274Z",
  "score": 83,
  "sourceWeight": 84,
  "tags": [
    "AI",
    "全球",
    "金融"
  ],
  "rank": 1,
  "contentStatus": "fetch-failed",
  "chineseTitle": "Ahrefs 的 Agent A",
  "chineseSummary": "由 Ahrefs 数据讨论支持的人工智能营销代理 |关联",
  "chineseContent": "由 Ahrefs 数据讨论支持的人工智能营销代理 |关联",
  "whyItMatters": "这条信息属于 AI 与科技趋势信号，适合用于观察工具选型、产品机会、开发者关注点和技术路线变化。",
  "translationStatus": "translated"
}