{
  "source": "Yahoo Finance",
  "category": "finance",
  "originalTitle": "Astrazeneca (AZN) Stock Dips While Market Gains: Key Facts",
  "summary": "The latest trading day saw Astrazeneca (AZN) settling at $171.61, representing a -3.85% change from its previous close.",
  "url": "https://finance.yahoo.com/markets/stocks/articles/astrazeneca-azn-stock-dips-while-221505061.html?.tsrc=rss",
  "publishedAt": "2026-07-10T22:15:05.000Z",
  "id": "yahoo-finance-448b32d7",
  "slug": "yahoo-finance-448b32d7",
  "content": "In the latest close session, Astrazeneca (AZN) was down 3.85% at $171.61. This move lagged the S&P 500's daily gain of 0.42%. Elsewhere, the Dow saw an upswing of 0.29%, while the tech-heavy Nasdaq appreciated by 0.29%.\n\nShares of the pharmaceutical witnessed a loss of 2.08% over the previous month, trailing the performance of the Medical sector with its gain of 5.6%, and the S&P 500's gain of 2.2%.\n\nInvestors will be eagerly watching for the performance of Astrazeneca in its upcoming earnings disclosure. The company's earnings report is set to be unveiled on July 27, 2026. The company is expected to report EPS of $2.52, up 15.6% from the prior-year quarter. Meanwhile, the latest consensus estimate predicts the revenue to be $15.27 billion, indicating a 5.65% increase compared to the same quarter of the previous year.\n\nRegarding the entire year, the Zacks Consensus Estimates forecast earnings of $10.28 per share and revenue of $63.45 billion, indicating changes of +12.23% and +8.01%, respectively, compared to the previous year.\n\nInvestors should also pay attention to any latest changes in analyst estimates for Astrazeneca. These recent revisions tend to reflect the evolving nature of short-term business trends. As such, positive estimate revisions reflect analyst optimism about the business and profitability.\n\nOur research demonstrates that these adjustments in estimates directly associate with imminent stock price performance. To exploit this, we've formed the Zacks Rank, a quantitative model that includes these estimate changes and presents a viable rating system.\n\nThe Zacks Rank system, ranging from #1 (Strong Buy) to #5 (Strong Sell), possesses a remarkable history of outdoing, externally audited, with #1 stocks returning an average annual gain of +25% since 1988. Over the past month, the Zacks Consensus EPS estimate has moved 0.26% higher. Right now, Astrazeneca possesses a Zacks Rank of #3 (Hold).\n\nIn terms of valuation, Astrazeneca is presently being traded at a Forward P/E ratio of 17.36. This represents a discount compared to its industry average Forward P/E of 20.47.\n\nOne should further note that AZN currently holds a PEG ratio of 1.45. The PEG ratio is similar to the widely-used P/E ratio, but this metric also takes the company's expected earnings growth rate into account. The Medical - Biomedical and Genetics industry currently had an average PEG ratio of 1.63 as of yesterday's close.\n\nThe Medical - Biomedical and Genetics industry is part of the Medical sector. This industry, currently bearing a Zacks Industry Rank of 106, finds itself in the top 44% echelons of all 250+ industries.\n\nThe strength of our individual industry groups is measured by the Zacks Industry Rank, which is calculated based on the average Zacks Rank of the individual stocks within these groups. Our research shows that the top 50% rated industries outperform the bottom half by a factor of 2 to 1.\n\nBe sure to follow all of these stock-moving metrics, and many more, on Zacks.com.\n\nWant the latest recommendations from Zacks Investment Research? Today, you can download 7 Best Stocks for the Next 30 Days. Click to get this free report\n\nAstraZeneca PLC (AZN) : Free Stock Analysis Report\n\nThis article originally published on Zacks Investment Research (zacks.com).",
  "fetchedAt": "2026-07-11T00:55:01.251Z",
  "score": 90,
  "sourceWeight": 82,
  "tags": [
    "全球",
    "金融"
  ],
  "rank": 23,
  "contentStatus": "article-extracted",
  "chineseTitle": "阿斯利康 (AZN) 股价下跌，而市场上涨：主要事实",
  "chineseSummary": "最新交易日阿斯利康 (AZN) 收于 171.61 美元，较前收盘价上涨 -3.85%。",
  "chineseContent": "在最近的收盘交易中，阿斯利康 (AZN) 下跌 3.85%，至 171.61 美元。这一举措落后于标准普尔 500 指数 0.42% 的日涨幅。其他方面，道指上涨 0.29%，而以科技股为主的纳斯达克指数则上涨 0.29%。\n\n该制药股较上月下跌 2.08%，落后于医疗板块 5.6% 的涨幅和标准普尔 500 指数 2.2% 的涨幅。\n\n投资者将热切关注阿斯利康在即将披露的财报中的表现。该公司的收益报告将于2026年7月27日公布。预计该公司的每股收益为2.52美元，比上年同期增长15.6%。与此同时，最新的共识预测收入为152.7亿美元，较去年同期增长5.65%。\n\n就全年而言，Zacks 一致预期每股收益为 10.28 美元，营收为 634.5 亿美元，与上年相比分别变化 +12.23% 和 +8.01%。\n\n投资者还应关注分析师对阿斯利康预测的最新变化。这些最近的修订往往反映了短期业务趋势不断变化的性质。因此，积极的估计修正反映了分析师对业务和盈利能力的乐观态度。\n\n我们的研究表明，这些预估调整与即将到来的股价表现直接相关。为了利用这一点，我们形成了 Zacks Rank，这是一个定量模型，其中包括这些估计变化并提供了一个可行的评级系统。\n\nZacks Rank 系统的范围从#1（强力买入）到#5（强力卖出），拥有卓越的超越历史，经过外部审计，自 1988 年以来，#1 股票的平均年涨幅为 +25%。在过去的一个月里，Zacks 共识 EPS 估计上升了 0.26%。目前，阿斯利康的 Zacks 排名为#3（持有）。\n\n就估值而言，阿斯利康目前的远期市盈率为17.36。这与其行业平均远期市盈率 20.47 相比有折扣。\n\n还应该指出的是，AZN 目前的 PEG 比率为 1.45。 PEG比率与广泛使用的市盈率类似，但该指标也考虑了公司的预期盈利增长率。截至昨天收盘，医疗 - 生物医学和遗传学行业目前的平均 PEG 率为 1.63。\n\n医疗 - 生物医学和遗传学行业是医疗行业的一部分。该行业目前的 Zacks 行业排名为 106，在所有 250 多个行业中处于前 44% 的梯队。\n\n我们各个行业组的实力是通过 Zacks 行业排名来衡量的，该排名是根据这些组中个股的平均 Zacks 排名计算的。我们的研究表明，排名前 50% 的行业的表现比排名后一半的行业高出 2 比 1。\n\n请务必遵循 Zacks.com 上的所有这些库存变动指标以及更多指标。\n\n想要 Zacks Investment Research 的最新建议吗？今天，您可以下载未来 30 天内的 7 只最佳股票。点击获取这份免费报告\n\n阿斯利康 (AZN)：免费股票分析报告\n\n本文最初发表于 Zacks Investment Research (zacks.com)。",
  "whyItMatters": "这条信息属于财经市场信号，适合用于观察利率、汇率、股债商品、金融机构和宏观政策变化。",
  "translationStatus": "translated"
}