{
  "source": "YouTube",
  "category": "youtube",
  "originalTitle": "Brawl Talk: Kenji & Kaze's Baby?",
  "summary": "Brawl Stars · 4,931,247 views",
  "content": "Brawl Talk Freebie: https://link.brawlstars.com/voucher/7bae5a2d-2afa-4e58-8f9b-dab2d987834c 🍜 Ramen Rebellion: a story event that will change Katana Kingdom forever! 🧬 NanoPowers & Fusions 🍚 Food Fight, Cooking Combat and more game modes 🤖 2 New Brawlers! Nori and Wendy 🌐 Buffies, Skins, Hypercharges & way WAY MORE #RamenRebellion #BrawlStars #BrawlTalk",
  "url": "https://www.youtube.com/watch?v=pgGThZitPis",
  "publishedAt": "2026-06-27T15:00:06.000Z",
  "channelTitle": "Brawl Stars",
  "viewCount": 4931247,
  "id": "youtube-ae9cdc59",
  "slug": "youtube-ae9cdc59",
  "fetchedAt": "2026-06-28T01:32:01.695Z",
  "score": 85,
  "sourceWeight": 78,
  "tags": [
    "视频"
  ],
  "rank": 4,
  "contentStatus": "source-fulltext",
  "chineseTitle": "| 争 | 吵 | ： | 健 | 二 | 和 | 风 | 的 | 孩 | 子 | ？ |",
  "chineseSummary": "荒野乱斗 · 4,931,247 次观看",
  "chineseContent": "Brawl Talk 免费赠品：https://link.brawlstars.com/voucher/7bae5a2d-2afa-4e58-8f9b-dab2d987834c 🍜 拉面叛乱：一个将永远改变武士刀王国的故事事件！ 🧬 NanoPowers & Fusions 🍚 食物大战、烹饪战斗和更多游戏模式 🤖 2 个新英雄！诺里和温迪🌐布菲、皮肤、超充能等等#RamenRebellion #BrawlStars #BrawlTalk",
  "whyItMatters": "这条信息属于 YouTube 热门视频信号，适合用于观察大众注意力、内容叙事、传播主题和跨平台选题机会。",
  "translationStatus": "translated"
}