{
  "source": "YouTube",
  "category": "youtube",
  "originalTitle": "This Minecraft Mod slowly got HORRIFYING. (VERITY)",
  "summary": "Flamingo · 224,069 views",
  "content": "Thanks to @ThatMob for giving birth to Verity. I test out this Minecraft mod that's supposed to help you since im a noob on minecraft.. teh mod I used is here, viewer beware my computer hasn’t been hacked yet but https://www.curseforge.com/minecraft/mc-mods/verity-je",
  "url": "https://www.youtube.com/watch?v=1WHdHyxZuto",
  "publishedAt": "2026-07-12T20:58:32.000Z",
  "channelTitle": "Flamingo",
  "viewCount": 224069,
  "id": "youtube-70fbf81b",
  "slug": "youtube-70fbf81b",
  "fetchedAt": "2026-07-13T00:59:58.842Z",
  "score": 81,
  "sourceWeight": 78,
  "tags": [
    "视频"
  ],
  "rank": 6,
  "contentStatus": "source-fulltext",
  "chineseTitle": "| T | h | i | s | | M | i | n | e | c | r | a | f | t | | M | o | d | | s | l | o | w | l | y | | g | o | t | | H | O | R | R | I | F | Y | I | N | G | . | | ( | V | E | R | I | T | Y | ) |",
  "chineseSummary": "Flamingo · 224,069 views",
  "chineseContent": "Thanks to @ThatMob for giving birth to Verity. I test out this Minecraft mod that's supposed to help you since im a noob on minecraft.. teh mod I used is here, viewer beware my computer hasn’t been hacked yet but https://www.curseforge.com/minecraft/mc-mods/verity-je",
  "whyItMatters": "该条目已进入今日趋势池，后续可在翻译服务恢复后自动补全中文解读。",
  "translationStatus": "fallback"
}